[
  { "id": 1201, "name": "Mateo", "gender": "male", "origin": "spanish", "religion": "christian", "rarity": "common", "meaning": "Gift of God", "description": "Matthew; the most popular boy name in Spain today, a divine present." },
  { "id": 1202, "name": "Lucía", "gender": "female", "origin": "spanish", "religion": "christian", "rarity": "common", "meaning": "Light", "description": "Saint Lucy, the bringer of light; radiant and timeless." },
  { "id": 1203, "name": "Santiago", "gender": "male", "origin": "spanish", "religion": "christian", "rarity": "common", "meaning": "Saint James", "description": "Patron saint of Spain; a pilgrim and a warrior of faith." },
  { "id": 1204, "name": "Sofía", "gender": "female", "origin": "spanish", "religion": "christian", "rarity": "common", "meaning": "Wisdom", "description": "Elegant and intellectual; a classic name across the Spanish-speaking world." },
  { "id": 1205, "name": "Alejandro", "gender": "male", "origin": "spanish", "religion": "christian", "rarity": "common", "meaning": "Defender of mankind", "description": "Alexander the Great; a powerful protector and leader." },
  { "id": 1206, "name": "Valentina", "gender": "female", "origin": "spanish", "religion": "christian", "rarity": "common", "meaning": "Strong, healthy", "description": "Feminine of Valentine; romantic, brave, and full of life." },
  { "id": 1207, "name": "Diego", "gender": "male", "origin": "spanish", "religion": "christian", "rarity": "common", "meaning": "Supplanter, teacher", "description": "Dynamic and artistic; the painter Velázquez's first name." },
  { "id": 1208, "name": "Martina", "gender": "female", "origin": "spanish", "religion": "christian", "rarity": "common", "meaning": "Warlike, dedicated to Mars", "description": "Strong and energetic; a fighter with feminine grace." },
  { "id": 1209, "name": "Javier", "gender": "male", "origin": "spanish", "religion": "christian", "rarity": "rare", "meaning": "New house, bright", "description": "Saint Francis Xavier; a missionary to the East, adventurous." },
  { "id": 1210, "name": "Camila", "gender": "female", "origin": "spanish", "religion": "christian", "rarity": "common", "meaning": "Attendant at a religious ceremony", "description": "Mythological warrior maiden; fast, brave, and graceful." },
  { "id": 1211, "name": "Carlos", "gender": "male", "origin": "spanish", "religion": "christian", "rarity": "common", "meaning": "Free man", "description": "Royal name of Spanish kings; a strong and noble character." },
  { "id": 1212, "name": "Isabella", "gender": "female", "origin": "spanish", "religion": "christian", "rarity": "common", "meaning": "Devoted to God", "description": "Queen Isabella of Castile; romantic, regal, and timeless." },
  { "id": 1213, "name": "Adrián", "gender": "male", "origin": "spanish", "religion": "christian", "rarity": "common", "meaning": "From Hadria, dark one", "description": "A handsome and modern name with ancient Roman roots." },
  { "id": 1214, "name": "María", "gender": "female", "origin": "spanish", "religion": "christian", "rarity": "common", "meaning": "Wished-for child, bitter", "description": "The Virgin Mary; the most sacred feminine name in the Spanish world." },
  { "id": 1215, "name": "Miguel", "gender": "male", "origin": "spanish", "religion": "christian", "rarity": "common", "meaning": "Who is like God?", "description": "Archangel Michael; a heavenly warrior of light." },
  { "id": 1216, "name": "Paula", "gender": "female", "origin": "spanish", "religion": "christian", "rarity": "common", "meaning": "Small, humble", "description": "A simple and devout name; a woman of faith." },
  { "id": 1217, "name": "Daniel", "gender": "male", "origin": "spanish", "religion": "christian", "rarity": "common", "meaning": "God is my judge", "description": "The prophet in the lion's den; wise and courageous." },
  { "id": 1218, "name": "Elena", "gender": "female", "origin": "spanish", "religion": "christian", "rarity": "common", "meaning": "Torch, bright light", "description": "Helen of Troy; a radiant and classical beauty." },
  { "id": 1219, "name": "Pablo", "gender": "male", "origin": "spanish", "religion": "christian", "rarity": "common", "meaning": "Small, humble", "description": "Apostle Paul; a small but mighty voice of truth." },
  { "id": 1220, "name": "Alba", "gender": "female", "origin": "spanish", "religion": "neutral", "rarity": "common", "meaning": "Dawn, white", "description": "The first light of morning; pure, fresh, and hopeful." },
  { "id": 1221, "name": "Alvaro", "gender": "male", "origin": "spanish", "religion": "christian", "rarity": "common", "meaning": "Elf warrior, all guard", "description": "A strong, traditional name; a protector from the magical realm." },
  { "id": 1222, "name": "Carmen", "gender": "female", "origin": "spanish", "religion": "christian", "rarity": "common", "meaning": "Garden, song, vineyard", "description": "Our Lady of Mount Carmel; passionate and artistic." },
  { "id": 1223, "name": "Marcos", "gender": "male", "origin": "spanish", "religion": "christian", "rarity": "common", "meaning": "Warlike, dedicated to Mars", "description": "Evangelist Mark; a lion-hearted writer." },
  { "id": 1224, "name": "Julia", "gender": "female", "origin": "spanish", "religion": "christian", "rarity": "common", "meaning": "Youthful, soft-haired", "description": "Roman family name; fresh, lively, and classic." },
  { "id": 1225, "name": "Gonzalo", "gender": "male", "origin": "spanish", "religion": "christian", "rarity": "rare", "meaning": "Battle, war", "description": "A medieval knight's name; a valiant warrior." },
  { "id": 1226, "name": "Clara", "gender": "female", "origin": "spanish", "religion": "christian", "rarity": "common", "meaning": "Clear, bright, famous", "description": "Saint Clare; luminous and pure, a light to the world." },
  { "id": 1227, "name": "Iker", "gender": "male", "origin": "spanish", "religion": "neutral", "rarity": "rare", "meaning": "Visitation, good news", "description": "Basque origin; modern and fresh, very popular in Spain." },
  { "id": 1228, "name": "Adriana", "gender": "female", "origin": "spanish", "religion": "christian", "rarity": "common", "meaning": "From Hadria, dark one", "description": "A rich, deep name with ancient roots; elegant and mysterious." },
  { "id": 1229, "name": "Enrique", "gender": "male", "origin": "spanish", "religion": "christian", "rarity": "common", "meaning": "Ruler of the home", "description": "Henry; a royal, strong, and domestic leader." },
  { "id": 1230, "name": "Sara", "gender": "female", "origin": "spanish", "religion": "christian", "rarity": "common", "meaning": "Princess, lady", "description": "Biblical matriarch; noble, graceful, and timeless." },
  { "id": 1231, "name": "Andrés", "gender": "male", "origin": "spanish", "religion": "christian", "rarity": "common", "meaning": "Manly, brave", "description": "Andrew, the first apostle; a faithful and courageous man." },
  { "id": 1232, "name": "Inés", "gender": "female", "origin": "spanish", "religion": "christian", "rarity": "common", "meaning": "Chaste, pure", "description": "Saint Agnes; a lamb-like innocence and strength." },
  { "id": 1233, "name": "Hugo", "gender": "male", "origin": "spanish", "religion": "christian", "rarity": "common", "meaning": "Mind, intellect", "description": "Victor Hugo's name; a brilliant thinker and creative force." },
  { "id": 1234, "name": "Laia", "gender": "female", "origin": "spanish", "religion": "christian", "rarity": "rare", "meaning": "Eloquent, well-spoken", "description": "Catalan form of Eulalia; a sweet and intelligent presence." },
  { "id": 1235, "name": "Mario", "gender": "male", "origin": "spanish", "religion": "christian", "rarity": "common", "meaning": "Manly, dedicated to Mars", "description": "Strong and classic; a warrior's heart with a gentle smile." },
  { "id": 1236, "name": "Ana", "gender": "female", "origin": "spanish", "religion": "christian", "rarity": "common", "meaning": "Grace, favor", "description": "Simple, pure, and timeless; a gift of divine mercy." },
  { "id": 1237, "name": "Ángel", "gender": "male", "origin": "spanish", "religion": "christian", "rarity": "common", "meaning": "Angel, messenger", "description": "A heavenly being; a protector and a pure soul." },
  { "id": 1238, "name": "Noa", "gender": "female", "origin": "spanish", "religion": "christian", "rarity": "common", "meaning": "Motion, rest", "description": "A unisex name, often feminine; a fresh and peaceful breeze." },
  { "id": 1239, "name": "Rodrigo", "gender": "male", "origin": "spanish", "religion": "christian", "rarity": "common", "meaning": "Famous ruler", "description": "El Cid's name; a legendary hero of medieval Spain." },
  { "id": 1240, "name": "Lara", "gender": "female", "origin": "spanish", "religion": "christian", "rarity": "common", "meaning": "Famous, protection", "description": "Short and international; a bright and protective presence." },
  { "id": 1241, "name": "Jorge", "gender": "male", "origin": "spanish", "religion": "christian", "rarity": "common", "meaning": "Farmer, earthworker", "description": "George; a dragon slayer and a patron saint." },
  { "id": 1242, "name": "Carla", "gender": "female", "origin": "spanish", "religion": "christian", "rarity": "common", "meaning": "Free man", "description": "Feminine of Carlos; a strong and independent woman." },
  { "id": 1243, "name": "Iván", "gender": "male", "origin": "spanish", "religion": "christian", "rarity": "common", "meaning": "God is gracious", "description": "Ivan the Terrible; a name with power and divine favor." },
  { "id": 1244, "name": "Triana", "gender": "female", "origin": "spanish", "religion": "neutral", "rarity": "rare", "meaning": "From Triana, seville neighborhood", "description": "A place name; passionate, flamenco, and colorful." },
  { "id": 1245, "name": "Pedro", "gender": "male", "origin": "spanish", "religion": "christian", "rarity": "common", "meaning": "Rock, stone", "description": "Saint Peter; the solid rock upon which the church was built." },
  { "id": 1246, "name": "Marina", "gender": "female", "origin": "spanish", "religion": "christian", "rarity": "common", "meaning": "Of the sea", "description": "A coastal breeze; deep, calm, and full of mystery." },
  { "id": 1247, "name": "Fernando", "gender": "male", "origin": "spanish", "religion": "christian", "rarity": "common", "meaning": "Brave journey, peace", "description": "A king's name; an adventurous and courageous spirit." },
  { "id": 1248, "name": "Nerea", "gender": "female", "origin": "spanish", "religion": "neutral", "rarity": "rare", "meaning": "Mine, of the sea", "description": "Basque origin; a poetic and marine beauty." },
  { "id": 1249, "name": "David", "gender": "male", "origin": "spanish", "religion": "christian", "rarity": "common", "meaning": "Beloved", "description": "King David; a poet, warrior, and a man after God's heart." },
  { "id": 1250, "name": "Vega", "gender": "female", "origin": "spanish", "religion": "neutral", "rarity": "rare", "meaning": "Fertile plain, meadow", "description": "A starry name; wide open land and luminous skies." },
  { "id": 1251, "name": "Rafael", "gender": "male", "origin": "spanish", "religion": "christian", "rarity": "common", "meaning": "God has healed", "description": "Archangel of healing; an artistic and gentle protector." },
  { "id": 1252, "name": "Celia", "gender": "female", "origin": "spanish", "religion": "christian", "rarity": "common", "meaning": "Heavenly, blind", "description": "A sweet and musical name; a celestial song." },
  { "id": 1253, "name": "José", "gender": "male", "origin": "spanish", "religion": "christian", "rarity": "common", "meaning": "God will increase", "description": "Joseph, the earthly father of Jesus; a just and quiet man." },
  { "id": 1254, "name": "Ainhoa", "gender": "female", "origin": "spanish", "religion": "christian", "rarity": "rare", "meaning": "Reference to the Virgin of Ainhoa", "description": "Basque town; a unique and spiritual name." },
  { "id": 1255, "name": "Guillermo", "gender": "male", "origin": "spanish", "religion": "christian", "rarity": "common", "meaning": "Resolute protector", "description": "William; a strong-willed and loyal guardian." },
  { "id": 1256, "name": "Beatriz", "gender": "female", "origin": "spanish", "religion": "christian", "rarity": "common", "meaning": "She who brings happiness", "description": "Dante's muse; a source of joy and inspiration." },
  { "id": 1257, "name": "Alberto", "gender": "male", "origin": "spanish", "religion": "christian", "rarity": "common", "meaning": "Noble, bright", "description": "A bright and distinguished gentleman; intelligent and kind." },
  { "id": 1258, "name": "Raquel", "gender": "female", "origin": "spanish", "religion": "christian", "rarity": "common", "meaning": "Ewe, lamb", "description": "Rachel; a gentle and beautiful biblical shepherdess." },
  { "id": 1259, "name": "Oscar", "gender": "male", "origin": "spanish", "religion": "christian", "rarity": "rare", "meaning": "Deer lover, God's spear", "description": "A cinematic award; a friendly and adventurous name." },
  { "id": 1260, "name": "Mireia", "gender": "female", "origin": "spanish", "religion": "neutral", "rarity": "rare", "meaning": "Admirable, to admire", "description": "Catalan name; a wondrous and stunning beauty." },
  { "id": 1261, "name": "Roberto", "gender": "male", "origin": "spanish", "religion": "christian", "rarity": "common", "meaning": "Bright fame", "description": "A famous and brilliant man; a shining star." },
  { "id": 1262, "name": "Alicia", "gender": "female", "origin": "spanish", "religion": "christian", "rarity": "common", "meaning": "Noble, of noble kind", "description": "Alice in Wonderland; a curious and adventurous spirit." },
  { "id": 1263, "name": "Tomás", "gender": "male", "origin": "spanish", "religion": "christian", "rarity": "common", "meaning": "Twin", "description": "Doubting Thomas; an honest and inquisitive man." },
  { "id": 1264, "name": "Lola", "gender": "female", "origin": "spanish", "religion": "christian", "rarity": "rare", "meaning": "Sorrows, lady of sorrows", "description": "A spunky, flamenco-loving name; full of passion." },
  { "id": 1265, "name": "Héctor", "gender": "male", "origin": "spanish", "religion": "cultural", "rarity": "rare", "meaning": "Holding fast, steadfast", "description": "Trojan hero; a loyal and brave defender." },
  { "id": 1266, "name": "Macarena", "gender": "female", "origin": "spanish", "religion": "christian", "rarity": "rare", "meaning": "Blessed, happy", "description": "The Virgin of Macarena; a joyful and festive name." },
  { "id": 1267, "name": "Eduardo", "gender": "male", "origin": "spanish", "religion": "christian", "rarity": "common", "meaning": "Wealthy guardian", "description": "A rich protector of home and family; noble and kind." },
  { "id": 1268, "name": "Eva", "gender": "female", "origin": "spanish", "religion": "christian", "rarity": "common", "meaning": "Life, living one", "description": "The first woman; a mother of all living." },
  { "id": 1269, "name": "Felipe", "gender": "male", "origin": "spanish", "religion": "christian", "rarity": "common", "meaning": "Lover of horses", "description": "King of Spain; a noble and elegant equestrian." },
  { "id": 1270, "name": "Olalla", "gender": "female", "origin": "spanish", "religion": "christian", "rarity": "rare", "meaning": "Well-spoken", "description": "Saint Eulalia; an eloquent and saintly maiden." },
  { "id": 1271, "name": "Julián", "gender": "male", "origin": "spanish", "religion": "christian", "rarity": "common", "meaning": "Youthful, downy-bearded", "description": "A young and vibrant man; a classic Roman name." },
  { "id": 1272, "name": "Diana", "gender": "female", "origin": "spanish", "religion": "neutral", "rarity": "common", "meaning": "Goddess of the hunt, divine", "description": "Roman goddess of the moon; a free and independent spirit." },
  { "id": 1273, "name": "Cristian", "gender": "male", "origin": "spanish", "religion": "christian", "rarity": "common", "meaning": "Follower of Christ", "description": "A modern name of faith; devoted and clear." },
  { "id": 1274, "name": "Aitana", "gender": "female", "origin": "spanish", "religion": "neutral", "rarity": "rare", "meaning": "Glory, from the mountain", "description": "A mountain range in Spain; a majestic and natural beauty." },
  { "id": 1275, "name": "Manuel", "gender": "male", "origin": "spanish", "religion": "christian", "rarity": "common", "meaning": "God is with us", "description": "Emmanuel; a comforting and divine presence." },
  { "id": 1276, "name": "Esther", "gender": "female", "origin": "spanish", "religion": "christian", "rarity": "common", "meaning": "Star, hidden", "description": "The Jewish queen who saved her people; a bright heroine." },
  { "id": 1277, "name": "Ramiro", "gender": "male", "origin": "spanish", "religion": "christian", "rarity": "rare", "meaning": "Famous advice, wise", "description": "A medieval king's name; a wise counselor." },
  { "id": 1278, "name": "Débora", "gender": "female", "origin": "spanish", "religion": "christian", "rarity": "rare", "meaning": "Bee", "description": "A biblical judge; industrious, wise, and a leader." },
  { "id": 1279, "name": "Saúl", "gender": "male", "origin": "spanish", "religion": "christian", "rarity": "rare", "meaning": "Asked for, prayed for", "description": "First king of Israel; a tall, chosen, and complex man." },
  { "id": 1280, "name": "Nuria", "gender": "female", "origin": "spanish", "religion": "christian", "rarity": "rare", "meaning": "Fire of the Lord, from Nuria valley", "description": "Catalan Marian shrine; a fiery and holy spirit." },
  { "id": 1281, "name": "Emilio", "gender": "male", "origin": "spanish", "religion": "christian", "rarity": "common", "meaning": "Rival, eager", "description": "A charming and competitive spirit; a classic name." },
  { "id": 1282, "name": "Gloria", "gender": "female", "origin": "spanish", "religion": "christian", "rarity": "common", "meaning": "Glory, fame", "description": "A woman of great renown and heavenly splendor." },
  { "id": 1283, "name": "Joaquín", "gender": "male", "origin": "spanish", "religion": "christian", "rarity": "rare", "meaning": "Established by God", "description": "Father of the Virgin Mary; a patient and holy man." },
  { "id": 1284, "name": "Teresa", "gender": "female", "origin": "spanish", "religion": "christian", "rarity": "common", "meaning": "Harvester, summer", "description": "Saint Teresa of Avila; a mystic and reformer." },
  { "id": 1285, "name": "Víctor", "gender": "male", "origin": "spanish", "religion": "christian", "rarity": "common", "meaning": "Victor, conqueror", "description": "A champion; successful and triumphant in all things." },
  { "id": 1286, "name": "Patricia", "gender": "female", "origin": "spanish", "religion": "christian", "rarity": "common", "meaning": "Noble, patrician", "description": "An aristocratic and refined lady; a true noble." },
  { "id": 1287, "name": "Damián", "gender": "male", "origin": "spanish", "religion": "christian", "rarity": "rare", "meaning": "To tame, subdue", "description": "Saint Damian; a healer and a gentle tamer of hearts." },
  { "id": 1288, "name": "Rocío", "gender": "female", "origin": "spanish", "religion": "christian", "rarity": "rare", "meaning": "Dew, morning dew", "description": "The Virgin of the Dew; a fresh and pure Andalusian devotion." },
  { "id": 1289, "name": "Luis", "gender": "male", "origin": "spanish", "religion": "christian", "rarity": "common", "meaning": "Famous warrior", "description": "A royal and classic name; a brave and renowned soldier." },
  { "id": 1290, "name": "Mónica", "gender": "female", "origin": "spanish", "religion": "christian", "rarity": "common", "meaning": "Advisor, alone", "description": "Saint Monica; the patient mother of Saint Augustine." },
  { "id": 1291, "name": "Ismael", "gender": "male", "origin": "spanish", "religion": "christian", "rarity": "rare", "meaning": "God will hear", "description": "Son of Abraham; the father of a great nation." },
  { "id": 1292, "name": "Natàlia", "gender": "female", "origin": "spanish", "religion": "christian", "rarity": "common", "meaning": "Christmas day, birth", "description": "A festive and warm name; a child of the holiday." },
  { "id": 1293, "name": "Adán", "gender": "male", "origin": "spanish", "religion": "christian", "rarity": "rare", "meaning": "Man, earth", "description": "The first man; a foundational and primal name." },
  { "id": 1294, "name": "Azucena", "gender": "female", "origin": "spanish", "religion": "neutral", "rarity": "rare", "meaning": "White lily", "description": "A pure and fragrant flower; delicate and beautiful." },
  { "id": 1295, "name": "Bautista", "gender": "male", "origin": "spanish", "religion": "christian", "rarity": "rare", "meaning": "Baptist, immerser", "description": "John the Baptist; a voice crying in the wilderness." },
  { "id": 1296, "name": "Abril", "gender": "female", "origin": "spanish", "religion": "neutral", "rarity": "rare", "meaning": "April, opening spring", "description": "A fresh and youthful month; full of blossoms." },
  { "id": 1297, "name": "César", "gender": "male", "origin": "spanish", "religion": "christian", "rarity": "rare", "meaning": "Long-haired, cut, emperor", "description": "Julius Caesar; an imperial and commanding presence." },
  { "id": 1298, "name": "Belén", "gender": "female", "origin": "spanish", "religion": "christian", "rarity": "rare", "meaning": "House of bread, Bethlehem", "description": "The birthplace of Jesus; a humble and sacred place." },
  { "id": 1299, "name": "Fabio", "gender": "male", "origin": "spanish", "religion": "christian", "rarity": "rare", "meaning": "Bean grower", "description": "A handsome Roman name; a charming and rustic man." },
  { "id": 1300, "name": "Angélica", "gender": "female", "origin": "spanish", "religion": "christian", "rarity": "rare", "meaning": "Angelic, like an angel", "description": "Heavenly and ethereal; a woman of pure beauty." }
]
